cbrf/__init__.py
cbrf/api.py
cbrf/const.py
cbrf/models.py
cbrf/tests.py
cbrf/utils.py
cbrf/asyncio/__init__.py
cbrf/asyncio/api.py
cbrf/asyncio/models.py
cbrf-1.0.0.dist-info/LICENSE
cbrf-1.0.0.dist-info/METADATA
cbrf-1.0.0.dist-info/WHEEL
cbrf-1.0.0.dist-info/top_level.txt
cbrf-1.0.0.dist-info/RECORD
