Metadata-Version: 2.1
Name: cbrf
Version: 1.0.0
Summary: Wrapper for The Central Bank of the Russian Federation site API
Home-page: https://github.com/egregors/cbrf
Author: Vadim Iskuchekov (@egregors)
Author-email: egregors@pm.me
License: MIT
Classifier: Development Status :: 5 - Production/Stable
Classifier: Environment :: Web Environment
Classifier: Intended Audience :: Developers
Classifier: License :: OSI Approved :: BSD License
Classifier: Operating System :: OS Independent
Classifier: Programming Language :: Python
Classifier: Programming Language :: Python :: 3.8
License-File: LICENSE
Requires-Dist: requests
Requires-Dist: aiohttp
